[
  {
    "code": "002938",
    "name": "",
    "analysis_result": {
      "code": "002938",
      "name": "",
      "should_exclude": false,
      "reason": "",
      "analysis": "该股票在近一个月股价呈现波动后回升，近半年涨幅约46.9%，财务数据显示净利润波动但2024年有所回升，不符合排除标准。"
    }
  },
  {
    "code": "000988",
    "name": "",
    "analysis_result": {
      "code": "000988",
      "name": "",
      "should_exclude": false,
      "reason": "",
      "analysis": "该股票近一个月股价呈上涨趋势，近半年涨幅约45.7%，财务报表显示净利润持续增长，不符合排除标准。"
    }
  },
  {
    "code": "300570",
    "name": "",
    "analysis_result": {
      "code": "300570",
      "name": "",
      "should_exclude": true,
      "reason": "涨幅巨大，炒作接近泡沫",
      "analysis": "该股票近一个月股价呈强劲上涨趋势，近半年涨幅高达57.6%，存在估值过高和泡沫风险，因此予以排除。"
    }
  },
  {
    "code": "603019",
    "name": "",
    "analysis_result": {
      "code": "603019",
      "name": "",
      "should_exclude": false,
      "reason": "",
      "analysis": "该股票近一个月股价呈上涨趋势，近半年涨幅约29.5%，财务数据净利润持续增长，不符合排除标准。"
    }
  },
  {
    "code": "002371",
    "name": "",
    "analysis_result": {
      "code": "002371",
      "name": "",
      "should_exclude": false,
      "reason": "",
      "analysis": "该股票近一个月股价呈上涨趋势，近半年涨幅约20.09%，财务数据显示净利润强劲且持续增长，不符合排除标准。"
    }
  },
  {
    "code": "603606",
    "name": "",
    "analysis_result": {
      "code": "603606",
      "name": "",
      "should_exclude": false,
      "reason": "",
      "analysis": "该股票近一个月股价呈上涨趋势，近半年涨幅约13.12%，财务数据净利润虽有波动但总体稳定，不符合排除标准。"
    }
  },
  {
    "code": "600900",
    "name": "",
    "analysis_result": {
      "code": "600900",
      "name": "",
      "should_exclude": false,
      "reason": "",
      "analysis": "该股票近一个月股价维持窄幅震荡，略有下跌但未形成持续下跌趋势，近半年涨幅仅约4.34%，财务报表显示稳健增长，不符合排除标准。"
    }
  },
  {
    "code": "300763",
    "name": "",
    "analysis_result": {
      "should_exclude": true,
      "reason": "分析失败",
      "analysis": "未能从AI获取对此股票的有效分析。请检查日志中AI的原始响应。"
    }
  },
  {
    "code": "600298",
    "name": "",
    "analysis_result": {
      "should_exclude": true,
      "reason": "分析失败",
      "analysis": "未能从AI获取对此股票的有效分析。请检查日志中AI的原始响应。"
    }
  },
  {
    "code": "600519",
    "name": "",
    "analysis_result": {
      "code": "600519",
      "name": "",
      "should_exclude": false,
      "reason": "",
      "analysis": "该股票近一个月股价呈震荡趋势，未出现明显下跌，近半年股价略有下跌，且财务报表显示强劲的净利润增长，不符合排除标准。"
    }
  }
]