[
  {
    "code": "300308",
    "name": "",
    "analysis_result": {
      "code": "300308",
      "name": "",
      "should_exclude": true,
      "reason": "涨幅巨大，炒作接近泡沫",
      "analysis": "近半年股价从低点（约80元）大幅上涨至170元以上，涨幅超过一倍，可能存在估值过高和泡沫风险。"
    }
  },
  {
    "code": "002463",
    "name": "",
    "analysis_result": {
      "code": "002463",
      "name": "",
      "should_exclude": true,
      "reason": "涨幅巨大，炒作接近泡沫",
      "analysis": "近三个月股价从低点（约27元）上涨至近50元，涨幅近80%，存在估值过高风险；同时部分财务数据不完整，建议用户自行核实。"
    }
  },
  {
    "code": "601127",
    "name": "",
    "analysis_result": {
      "code": "601127",
      "name": "",
      "should_exclude": false,
      "reason": "",
      "analysis": "股价近期走势平稳，未出现明显下跌或巨大涨幅；但财务报表显示公司在2021-2023年连续亏损，2024年扭亏为盈，且存在部分财务数据不完整，建议用户仔细评估其基本面风险。"
    }
  },
  {
    "code": "605499",
    "name": "",
    "analysis_result": {
      "code": "605499",
      "name": "",
      "should_exclude": true,
      "reason": "近期明显下跌走势",
      "analysis": "股价在最近一个月内从高点（约338元）下跌至291元，跌幅超过10%，呈现明显下跌趋势且无企稳迹象。"
    }
  },
  {
    "code": "603486",
    "name": "",
    "analysis_result": {
      "code": "603486",
      "name": "",
      "should_exclude": true,
      "reason": "涨幅巨大，炒作接近泡沫",
      "analysis": "近三个月股价从低点（约42元）上涨至近70元，涨幅约66%，存在估值过高的风险。"
    }
  },
  {
    "code": "000803",
    "name": "",
    "analysis_result": {
      "code": "000803",
      "name": "",
      "should_exclude": true,
      "reason": "涨幅巨大，炒作接近泡沫",
      "analysis": "近三个月股价从低点（约4.3元）上涨至7元以上，涨幅约65%，存在估值过高的风险。"
    }
  },
  {
    "code": "301031",
    "name": "",
    "analysis_result": {
      "code": "301031",
      "name": "",
      "should_exclude": false,
      "reason": "",
      "analysis": "股价近半年涨幅约16.8%，未出现明显下跌或巨大涨幅；但部分财务数据不完整且净有形资产为负，建议用户自行核实并评估其基本面风险。"
    }
  },
  {
    "code": "603993",
    "name": "",
    "analysis_result": {
      "should_exclude": true,
      "reason": "分析失败",
      "analysis": "未能从AI获取对此股票的有效分析。请检查日志中AI的原始响应。"
    }
  },
  {
    "code": "600176",
    "name": "",
    "analysis_result": {
      "code": "600176",
      "name": "",
      "should_exclude": false,
      "reason": "",
      "analysis": "股价近半年走势平稳，未出现明显下跌或巨大涨幅；但关键财务数据（特别是现金流量表部分）严重缺失，建议用户自行核实相关财务报表。"
    }
  },
  {
    "code": "600801",
    "name": "",
    "analysis_result": {
      "should_exclude": true,
      "reason": "分析失败",
      "analysis": "未能从AI获取对此股票的有效分析。请检查日志中AI的原始响应。"
    }
  }
]