[
  {
    "code": "300308",
    "name": "",
    "analysis_result": {
      "code": "300308",
      "name": "",
      "should_exclude": true,
      "reason": "涨幅巨大，炒作接近泡沫",
      "analysis": "该股在过去半年内股价涨幅巨大，从年初低点至今已翻倍，存在估值过高和泡沫风险。"
    }
  },
  {
    "code": "002938",
    "name": "",
    "analysis_result": {
      "code": "002938",
      "name": "",
      "should_exclude": true,
      "reason": "涨幅巨大，炒作接近泡沫",
      "analysis": "该股在过去半年内经历显著上涨，尤其近一个月涨幅较大，可能存在估值过高和泡沫风险。"
    }
  },
  {
    "code": "000400",
    "name": "",
    "analysis_result": {
      "code": "000400",
      "name": "",
      "should_exclude": false,
      "reason": "",
      "analysis": "该股近半年股价波动相对平稳，未出现明显下跌走势或巨大涨幅，不符合排除标准。"
    }
  },
  {
    "code": "603993",
    "name": "",
    "analysis_result": {
      "code": "603993",
      "name": "",
      "should_exclude": false,
      "reason": "",
      "analysis": "该股近半年股价整体上涨幅度有限，且近期未出现明显持续下跌，不符合排除标准。"
    }
  },
  {
    "code": "301070",
    "name": "",
    "analysis_result": {
      "code": "301070",
      "name": "",
      "should_exclude": true,
      "reason": "涨幅巨大，炒作接近泡沫",
      "analysis": "该股在过去半年内经历过近乎翻倍的股价涨幅，虽然近期有所回调，但短期内涨幅过大，存在泡沫风险。"
    }
  },
  {
    "code": "002276",
    "name": "",
    "analysis_result": {
      "code": "002276",
      "name": "",
      "should_exclude": true,
      "reason": "涨幅巨大，炒作接近泡沫",
      "analysis": "该股在过去半年内股价涨幅接近80%，属于巨大涨幅，可能存在估值过高和泡沫风险。"
    }
  },
  {
    "code": "600801",
    "name": "",
    "analysis_result": {
      "code": "600801",
      "name": "",
      "should_exclude": false,
      "reason": "",
      "analysis": "该股近半年股价走势平稳，未出现明显下跌或巨大涨幅，不符合排除标准。"
    }
  },
  {
    "code": "002624",
    "name": "",
    "analysis_result": {
      "should_exclude": true,
      "reason": "分析失败",
      "analysis": "未能从AI获取对此股票的有效分析。请检查日志中AI的原始响应。"
    }
  },
  {
    "code": "300476",
    "name": "",
    "analysis_result": {
      "code": "300476",
      "name": "",
      "should_exclude": true,
      "reason": "涨幅巨大，炒作接近泡沫",
      "analysis": "该股在过去半年内股价涨幅超过100%，属于非常巨大的涨幅，存在估值过高和泡沫风险。"
    }
  },
  {
    "code": "002028",
    "name": "",
    "analysis_result": {
      "should_exclude": true,
      "reason": "分析失败",
      "analysis": "未能从AI获取对此股票的有效分析。请检查日志中AI的原始响应。"
    }
  }
]