[
  {
    "code": "300693",
    "name": "盛弘股份",
    "analysis_result": {
      "code": "300693",
      "should_exclude": false,
      "reason": "",
      "analysis": "盛弘股份在过去几年盈利持续增长，负债率保持在合理水平，现金流健康，近期股价无明显持续下跌趋势，也无明显泡沫风险，不予排除。"
    }
  },
  {
    "code": "002600",
    "name": "领益智造",
    "analysis_result": {
      "code": "002600",
      "should_exclude": false,
      "reason": "",
      "analysis": "领益智造财务表现总体健康，盈利能力和现金流稳定，负债率合理，近期股价未出现明显下跌或泡沫化趋势，不予排除。"
    }
  },
  {
    "code": "002050",
    "name": "三花智控",
    "analysis_result": {
      "code": "002050",
      "should_exclude": false,
      "reason": "",
      "analysis": "三花智控业绩持续增长，财务状况稳健，现金流充裕，近期股价波动正常，不予排除。"
    }
  },
  {
    "code": "600415",
    "name": "小商品城",
    "analysis_result": {
      "code": "600415",
      "should_exclude": true,
      "reason": "涨幅巨大，炒作接近泡沫",
      "analysis": "小商品城在过去半年股价涨幅巨大（超过60%），存在估值过高和泡沫风险，建议排除观察。"
    }
  },
  {
    "code": "301171",
    "name": "易点天下",
    "analysis_result": {
      "code": "301171",
      "should_exclude": false,
      "reason": "",
      "analysis": "易点天下财务状况非常健康，盈利和现金流稳定，负债率低，近期股价也无异常波动，不予排除。"
    }
  },
  {
    "code": "301565",
    "name": "中仑新材",
    "analysis_result": {
      "should_exclude": true,
      "reason": "分析失败",
      "analysis": "未能从AI获取对此股票的有效分析。请检查日志中AI的原始响应。"
    }
  },
  {
    "code": "300316",
    "name": "晶盛机电",
    "analysis_result": {
      "code": "300316",
      "should_exclude": false,
      "reason": "",
      "analysis": "晶盛机电财务稳健，尽管2024年净利润有所下滑，但仍保持高盈利能力和健康现金流，近期股价无明显趋势，不予排除。"
    }
  },
  {
    "code": "000960",
    "name": "锡业股份",
    "analysis_result": {
      "code": "000960",
      "should_exclude": false,
      "reason": "",
      "analysis": "锡业股份盈利能力虽有波动但保持健康，负债率持续改善，现金流充裕，近期股价未出现泡沫或持续下跌，不予排除。"
    }
  },
  {
    "code": "300674",
    "name": "宇信科技",
    "analysis_result": {
      "should_exclude": true,
      "reason": "分析失败",
      "analysis": "未能从AI获取对此股票的有效分析。请检查日志中AI的原始响应。"
    }
  },
  {
    "code": "603383",
    "name": "顶点软件",
    "analysis_result": {
      "code": "603383",
      "should_exclude": false,
      "reason": "",
      "analysis": "顶点软件财务状况优秀，盈利能力强劲，负债率持续降低，现金流健康，近期股价表现正常，不予排除。"
    }
  },
  {
    "code": "600060",
    "name": "海信视像",
    "analysis_result": {
      "should_exclude": true,
      "reason": "分析失败",
      "analysis": "未能从AI获取对此股票的有效分析。请检查日志中AI的原始响应。"
    }
  }
]