[
  {
    "code": "601138",
    "name": "",
    "analysis_result": {
      "code": "601138",
      "name": "",
      "should_exclude": true,
      "reason": "涨幅巨大接近泡沫",
      "analysis": "该股票在过去三个月内涨幅超过50%，近期股价快速拉升，可能存在估值过高和泡沫风险。"
    }
  },
  {
    "code": "002463",
    "name": "",
    "analysis_result": {
      "code": "002463",
      "name": "",
      "should_exclude": true,
      "reason": "涨幅巨大接近泡沫",
      "analysis": "该股票在过去两个多月内涨幅接近80%，股价快速拉升，可能存在估值过高和泡沫风险。"
    }
  },
  {
    "code": "600160",
    "name": "",
    "analysis_result": {
      "code": "600160",
      "name": "",
      "should_exclude": false,
      "reason": null,
      "analysis": "该股票在过去半年内涨幅不明显，近期股价略有波动但未出现持续下跌趋势，财务表现存在波动性，需进一步深入分析长期价值。"
    }
  },
  {
    "code": "601127",
    "name": "",
    "analysis_result": {
      "code": "601127",
      "name": "",
      "should_exclude": false,
      "reason": null,
      "analysis": "该股票在过去半年内股价波动但未出现巨大涨幅或持续下跌趋势，最新财报显示公司业绩出现显著改善，有待长期关注。"
    }
  },
  {
    "code": "300433",
    "name": "",
    "analysis_result": {
      "code": "300433",
      "name": "",
      "should_exclude": false,
      "reason": null,
      "analysis": "该股票在过去半年内涨幅不明显，近期虽有波动但未形成持续下跌趋势，公司财务报表显示稳健增长，具长期关注价值。"
    }
  },
  {
    "code": "300138",
    "name": "",
    "analysis_result": {
      "code": "300138",
      "name": "",
      "should_exclude": true,
      "reason": "涨幅巨大接近泡沫",
      "analysis": "该股票在过去半年内涨幅巨大超过65%，同时2024年净利润大幅下滑且自由现金流持续为负，股价上涨可能存在泡沫和脱离基本面情况。"
    }
  },
  {
    "code": "002597",
    "name": "",
    "analysis_result": {
      "should_exclude": true,
      "reason": "分析失败",
      "analysis": "未能从AI获取对此股票的有效分析。请检查日志中AI的原始响应。"
    }
  },
  {
    "code": "002541",
    "name": "",
    "analysis_result": {
      "code": "002541",
      "name": "",
      "should_exclude": false,
      "reason": null,
      "analysis": "该股票在过去半年内涨幅不明显，近期股价略有波动但未出现持续下跌趋势，但公司营收、净利润和自由现金流在2024年均出现恶化，需警惕长期风险。"
    }
  },
  {
    "code": "600900",
    "name": "",
    "analysis_result": {
      "code": "600900",
      "name": "",
      "should_exclude": false,
      "reason": null,
      "analysis": "该股票在过去半年内股价波动不大且未出现明显下跌或巨大涨幅，公司财务表现持续稳健增长，具有较好的长期投资价值。"
    }
  },
  {
    "code": "000729",
    "name": "",
    "analysis_result": {
      "code": "000729",
      "name": "",
      "should_exclude": false,
      "reason": null,
      "analysis": "该股票在过去半年内涨幅不明显，近期股价略有波动但未出现持续下跌趋势，公司财务表现持续稳健增长，具有较好的长期投资价值。"
    }
  }
]