[
  {
    "code": "601669",
    "name": "",
    "analysis_result": {
      "code": "601669",
      "name": "",
      "should_exclude": false,
      "reason": null,
      "analysis": "该股票近期股价呈上升趋势，未出现明显下跌；近半年涨幅约25%，不属于巨大炒作泡沫范围，财务数据较为完整且盈利能力稳定。"
    }
  },
  {
    "code": "000528",
    "name": "",
    "analysis_result": {
      "code": "000528",
      "name": "",
      "should_exclude": false,
      "reason": null,
      "analysis": "该股票近期股价出现上涨，而非持续下跌；近半年涨幅约20%，未达巨大泡沫水平，且财务数据较为完整并显示盈利能力改善。"
    }
  },
  {
    "code": "601633",
    "name": "",
    "analysis_result": {
      "code": "601633",
      "name": "",
      "should_exclude": false,
      "reason": null,
      "analysis": "该股票近期股价呈小幅下跌后企稳态势，未出现持续大幅下挫；近半年股价波动较大但整体趋势向上，未见泡沫化风险，财务数据完整且盈利稳定增长。"
    }
  },
  {
    "code": "603993",
    "name": "",
    "analysis_result": {
      "code": "603993",
      "name": "",
      "should_exclude": true,
      "reason": "涨幅巨大，炒作接近泡沫",
      "analysis": "该股票近半年股价从约5.95元飙升至9.04元，涨幅超过50%，且近期成交量巨大，存在估值过高和炒作风险。"
    }
  },
  {
    "code": "600111",
    "name": "",
    "analysis_result": {
      "code": "600111",
      "name": "",
      "should_exclude": true,
      "reason": "涨幅巨大，炒作接近泡沫",
      "analysis": "该股票近半年股价从约21.03元大幅上涨至34.36元，涨幅超过60%，短期内涨幅巨大，存在泡沫化风险，且近期波动剧烈。"
    }
  },
  {
    "code": "300308",
    "name": "",
    "analysis_result": {
      "code": "300308",
      "name": "",
      "should_exclude": true,
      "reason": "涨幅巨大，炒作接近泡沫",
      "analysis": "该股票近半年股价从约79.75元飙升至184.60元，涨幅巨大接近130%，存在明显的炒作泡沫风险，且近期波动剧烈。"
    }
  },
  {
    "code": "300502",
    "name": "",
    "analysis_result": {
      "code": "300502",
      "name": "",
      "should_exclude": true,
      "reason": "涨幅巨大，炒作接近泡沫",
      "analysis": "该股票近半年股价从约66.88元飙升至176.50元，涨幅巨大超过160%，存在明显的炒作泡沫风险，短期内表现出投机性上涨。"
    }
  },
  {
    "code": "601127",
    "name": "",
    "analysis_result": {
      "code": "601127",
      "name": "",
      "should_exclude": false,
      "reason": null,
      "analysis": "该股票近期股价保持在相对高位，未出现明显下跌趋势；近半年涨幅约10%，不属于巨大炒作泡沫范围，财务数据完整且盈利能力持续增强。"
    }
  },
  {
    "code": "300662",
    "name": "",
    "analysis_result": {
      "code": "300662",
      "name": "",
      "should_exclude": true,
      "reason": "近期明显下跌走势",
      "analysis": "该股票在过去一个月从约34.93元持续下跌至31.75元，跌幅约9%，且近两周继续震荡下行，下跌趋势明显，暂无企稳迹象。"
    }
  },
  {
    "code": "301511",
    "name": "",
    "analysis_result": {
      "code": "301511",
      "name": "",
      "should_exclude": true,
      "reason": "涨幅巨大，炒作接近泡沫",
      "analysis": "该股票近半年股价从约13.55元飙升至27.53元，涨幅超过100%，短期内涨幅巨大，存在明显的炒作泡沫风险。"
    }
  }
]