[
  {
    "code": "300308",
    "name": "",
    "analysis_result": {
      "code": "300308",
      "name": "",
      "should_exclude": true,
      "reason": "涨幅巨大，炒作接近泡沫",
      "analysis": "近半年股价涨幅巨大，从4月中旬的77元左右飙升至7月中旬的176元以上，涨幅超过100%。尽管公司营收和净利润增长强劲，但如此短期的快速上涨存在短期炒作和估值过高风险。"
    }
  },
  {
    "code": "002463",
    "name": "",
    "analysis_result": {
      "code": "002463",
      "name": "",
      "should_exclude": true,
      "reason": "涨幅巨大，炒作接近泡沫",
      "analysis": "近半年股价经历较大幅度上涨，特别是从5月初的29.5元左右上涨至7月中旬的53元以上，涨幅接近80%。虽然公司财务表现良好，营收和净利润均有增长，但短期涨幅过大，存在短期炒作风险，建议谨慎观察。"
    }
  },
  {
    "code": "002028",
    "name": "",
    "analysis_result": {
      "code": "002028",
      "name": "",
      "should_exclude": false,
      "reason": "",
      "analysis": "近半年股价表现相对稳健，涨幅温和。公司营收和净利润持续增长，财务状况良好，基本面未见明显风险。"
    }
  },
  {
    "code": "605499",
    "name": "",
    "analysis_result": {
      "code": "605499",
      "name": "",
      "should_exclude": false,
      "reason": "",
      "analysis": "近半年股价有所波动，但未出现清晰、持续的下跌趋势。公司财务报表显示营收和净利润持续高速增长，基本面支撑较强，未见明显泡沫风险。"
    }
  },
  {
    "code": "300680",
    "name": "",
    "analysis_result": {
      "code": "300680",
      "name": "",
      "should_exclude": true,
      "reason": "涨幅巨大，炒作接近泡沫",
      "analysis": "近半年股价从1月的23.6元飙升至3月的48.4元，涨幅超过100%，随后虽有回调但仍处于高位。而公司净利润体量相对较小且现金流波动较大，此番巨大涨幅与基本面不完全匹配，存在明显短期炒作和泡沫风险。"
    }
  },
  {
    "code": "002527",
    "name": "",
    "analysis_result": {
      "code": "002527",
      "name": "",
      "should_exclude": true,
      "reason": "涨幅巨大，炒作接近泡沫",
      "analysis": "近半年股价从1月的9.3元飙升至2月的19.6元，涨幅超过110%，此后虽有回调但仍处于高位。然而，公司营收波动，且近三年连续出现净利润为负的情况，现金流状况亦不佳。股价的巨大涨幅与糟糕的基本面严重背离，存在严重的炒作和泡沫风险。"
    }
  },
  {
    "code": "002938",
    "name": "",
    "analysis_result": {
      "code": "002938",
      "name": "",
      "should_exclude": false,
      "reason": "",
      "analysis": "近半年股价虽有快速上涨，但公司营收和净利润规模巨大且保持健康，现金流状况良好，整体财务基本面支撑较强，短期涨幅尚在合理范围内，未见明显泡沫风险。"
    }
  },
  {
    "code": "002080",
    "name": "",
    "analysis_result": {
      "code": "002080",
      "name": "",
      "should_exclude": true,
      "reason": "涨幅巨大，炒作接近泡沫",
      "analysis": "近半年股价从1月的10.6元上涨至7月中旬的26.7元，涨幅高达150%以上。然而，公司营收波动剧烈，2024年出现巨额亏损且自由现金流为负，股价表现与公司基本面严重脱节，存在极高炒作和泡沫风险。"
    }
  },
  {
    "code": "600732",
    "name": "",
    "analysis_result": {
      "code": "600732",
      "name": "",
      "should_exclude": true,
      "reason": "涨幅巨大，炒作接近泡沫",
      "analysis": "近半年股价从1月的9.5元上涨至7月中旬的15.1元，涨幅接近60%。但公司营收呈下滑趋势，2024年出现巨额净利润亏损，且自由现金流为负，股价的快速上涨缺乏基本面支撑，存在较大炒作和泡沫风险。"
    }
  },
  {
    "code": "002624",
    "name": "",
    "analysis_result": {
      "should_exclude": true,
      "reason": "分析失败",
      "analysis": "未能从AI获取对此股票的有效分析。请检查日志中AI的原始响应。"
    }
  }
]