[
  {
    "code": "601138",
    "name": "",
    "analysis_result": {
      "code": "601138",
      "name": "",
      "should_exclude": true,
      "reason": "涨幅巨大，炒作接近泡沫",
      "analysis": "股票在过去半年内（2025年3月5日至9月5日）从约20.63元上涨至约55.83元，涨幅超过170%，显示出巨大的涨幅，存在明显的炒作和潜在泡沫风险。"
    }
  },
  {
    "code": "002938",
    "name": "",
    "analysis_result": {
      "code": "002938",
      "name": "",
      "should_exclude": false,
      "reason": "",
      "analysis": "股票近期（最近1个月）价格波动较大，在9月初从高点有所回落，但整体在一个月内仍呈上涨态势（从约48.70元升至51.55元），未形成清晰、持续的下跌趋势。过去半年涨幅约35%，不符合“涨幅巨大，炒作接近泡沫”的排除标准。财务数据完整。"
    }
  },
  {
    "code": "300763",
    "name": "",
    "analysis_result": {
      "code": "300763",
      "name": "",
      "should_exclude": true,
      "reason": "涨幅巨大，炒作接近泡沫",
      "analysis": "股票在过去半年内（2025年3月5日至9月5日）从约49.96元上涨至约89.24元，涨幅近79%。尤其在近期出现加速上涨，存在明显的炒作和潜在泡沫风险。"
    }
  },
  {
    "code": "603009",
    "name": "",
    "analysis_result": {
      "code": "603009",
      "name": "",
      "should_exclude": true,
      "reason": "涨幅巨大，炒作接近泡沫",
      "analysis": "股票在过去半年内（2025年3月5日至9月5日）从约20.63元上涨至约45.99元，涨幅超过120%，已达到“涨幅巨大”的排除标准，存在潜在泡沫风险。"
    }
  },
  {
    "code": "300776",
    "name": "",
    "analysis_result": {
      "code": "300776",
      "name": "",
      "should_exclude": false,
      "reason": "",
      "analysis": "股票近期（最近1个月）价格波动，在8月底至9月初从高点有所回落，但整体在一个月内仍呈上涨态势（从约66.17元升至72.05元），未形成清晰、持续的下跌趋势。过去半年涨幅约13.7%，不符合“涨幅巨大，炒作接近泡沫”的排除标准。财务数据完整。"
    }
  },
  {
    "code": "600941",
    "name": "",
    "analysis_result": {
      "code": "600941",
      "name": "",
      "should_exclude": false,
      "reason": "",
      "analysis": "股票近期（最近1个月）价格走势相对平稳，未表现出清晰、持续的下跌趋势。过去半年涨幅仅约2.6%，不符合“涨幅巨大，炒作接近泡沫”的排除标准。财务数据完整。"
    }
  },
  {
    "code": "600900",
    "name": "",
    "analysis_result": {
      "code": "600900",
      "name": "",
      "should_exclude": false,
      "reason": "",
      "analysis": "股票近期（最近1个月）价格走势非常平稳，波动幅度小，未形成明显下跌或巨大涨幅的趋势。过去半年涨幅仅约4.7%，不符合“涨幅巨大，炒作接近泡沫”的排除标准。财务数据完整。"
    }
  },
  {
    "code": "300570",
    "name": "",
    "analysis_result": {
      "code": "300570",
      "name": "",
      "should_exclude": true,
      "reason": "近期明显下跌走势",
      "analysis": "股票在近期（从2025年9月1日约142.15元至9月4日约107.85元）出现显著、持续的下跌，跌幅超过24%，尽管9月5日有所反弹，但缺乏明确的企稳迹象。"
    }
  },
  {
    "code": "002648",
    "name": "",
    "analysis_result": {
      "should_exclude": true,
      "reason": "分析失败",
      "analysis": "未能从AI获取对此股票的有效分析。请检查日志中AI的原始响应。"
    }
  }
]