[
  {
    "code": "603920",
    "name": "世运电路",
    "analysis_result": {
      "code": "603920",
      "should_exclude": false,
      "reason": null,
      "analysis": "公司近期股价呈上涨趋势，在过去六个月内虽然经历回调但未有巨大泡沫迹象，且财务报表显示其持续盈利，负债率大幅下降，现金流强劲，财务状况健康。"
    }
  },
  {
    "code": "002436",
    "name": "兴森科技",
    "analysis_result": {
      "code": "002436",
      "should_exclude": true,
      "reason": "财务有严重问题",
      "analysis": "公司净利润连续下滑，2024年出现亏损，且负债率持续较高，自由现金流多年为负，财务状况存在严重风险。"
    }
  },
  {
    "code": "603859",
    "name": "能科科技",
    "analysis_result": {
      "code": "603859",
      "should_exclude": false,
      "reason": null,
      "analysis": "公司近期股价呈上涨趋势，未有巨大涨幅或泡沫迹象；财务上持续盈利，负债率可控，2024年自由现金流转正，财务状况稳健。"
    }
  },
  {
    "code": "300570",
    "name": "太辰光",
    "analysis_result": {
      "code": "300570",
      "should_exclude": true,
      "reason": "涨幅巨大，炒作接近泡沫",
      "analysis": "股票在过去一个月内涨幅高达42%，过去半年经历多轮快速上涨，股价波动剧烈，存在短期估值过高和投机泡沫风险。"
    }
  },
  {
    "code": "002600",
    "name": "领益智造",
    "analysis_result": {
      "code": "002600",
      "should_exclude": false,
      "reason": null,
      "analysis": "公司近期股价呈上涨趋势，未有巨大泡沫迹象；财务上持续盈利，负债水平可控，现金流状况保持健康，整体经营稳健。"
    }
  },
  {
    "code": "000537",
    "name": "中绿电",
    "analysis_result": {
      "code": "000537",
      "should_exclude": true,
      "reason": "财务有严重问题",
      "analysis": "公司负债率极高且持续恶化，近三年自由现金流持续为巨额负值，尽管近期实现盈利，但其财务结构风险巨大。"
    }
  },
  {
    "code": "601899",
    "name": "紫金矿业",
    "analysis_result": {
      "code": "601899",
      "should_exclude": false,
      "reason": null,
      "analysis": "公司近期股价呈上涨趋势，虽涨幅较大但得益于基本面支撑；财务报表显示其持续盈利能力强劲，自由现金流充裕，负债率虽高但呈改善趋势，经营稳健。"
    }
  },
  {
    "code": "300677",
    "name": "英科医疗",
    "analysis_result": {
      "code": "300677",
      "should_exclude": true,
      "reason": "财务有严重问题",
      "analysis": "公司净利润在2021年高峰后大幅下滑，近三年自由现金流持续为负，且负债率快速攀升，财务状况存在严重恶化迹象。"
    }
  },
  {
    "code": "301363",
    "name": "美好医疗",
    "analysis_result": {
      "code": "301363",
      "should_exclude": false,
      "reason": null,
      "analysis": "公司近期股价呈上涨趋势，未有巨大泡沫迹象；财务报表显示其持续盈利，负债水平极低，自由现金流稳定为正，财务状况非常健康。"
    }
  },
  {
    "code": "000100",
    "name": "TCL科技",
    "analysis_result": {
      "should_exclude": true,
      "reason": "分析失败",
      "analysis": "未能从AI获取对此股票的有效分析。请检查日志中AI的原始响应。"
    }
  },
  {
    "code": "600415",
    "name": "小商品城",
    "analysis_result": {
      "should_exclude": true,
      "reason": "分析失败",
      "analysis": "未能从AI获取对此股票的有效分析。请检查日志中AI的原始响应。"
    }
  },
  {
    "code": "603486",
    "name": "科沃斯",
    "analysis_result": {
      "code": "603486",
      "should_exclude": true,
      "reason": "财务有严重问题",
      "analysis": "公司净利润和自由现金流在2021年高峰后大幅下滑，尽管2024年有所回升，但与历史水平相比经营状况显著恶化，表明其核心业务面临挑战，存在长期价值风险。"
    }
  }
]